openrank_sdk/__init__.py
openrank_sdk/eigentrust_client.py
openrank_sdk/trust.py
openrank_sdk/utils.py
openrank_sdk-0.4.0.dist-info/METADATA
openrank_sdk-0.4.0.dist-info/WHEEL
openrank_sdk-0.4.0.dist-info/RECORD
