Metadata-Version: 2.1
Name: openrank-sdk
Version: 0.4.0
Summary: 
Author: SeungJu Lee
Author-email: sj@karma3labs.com
Requires-Python: >=3.9,<4.0
Classifier: Programming Language :: Python :: 3
Classifier: Programming Language :: Python :: 3.9
Classifier: Programming Language :: Python :: 3.10
Classifier: Programming Language :: Python :: 3.11
Classifier: Programming Language :: Python :: 3.12
Requires-Dist: boto3 (>=1.0)
Requires-Dist: dataclasses-json (>=0.6.7,<0.7.0)
Requires-Dist: httpx (>=0.6.7)
Requires-Dist: numpy (>=1.22.2)
Requires-Dist: pandas (>=1.4.0)
Requires-Dist: sphinx (>=7.1.0)
